RRG/__init__.py
RRG/analysis.py
RRG/renormalization.py
random_renormalization_group-0.1.1.dist-info/LICENSE
random_renormalization_group-0.1.1.dist-info/METADATA
random_renormalization_group-0.1.1.dist-info/WHEEL
random_renormalization_group-0.1.1.dist-info/top_level.txt
random_renormalization_group-0.1.1.dist-info/RECORD
