Metadata-Version: 2.1
Name: random_renormalization_group
Version: 0.1.1
Summary: The package for random renormalization group
Home-page: https://github.com/Asuka-Research-Group/Random-renormalization-group
Author: Yang Tian, Pei Sun and Yizhou Xu
Classifier: Programming Language :: Python :: 3
Classifier: License :: OSI Approved :: MIT License
Classifier: Operating System :: OS Independent
Requires-Python: >=3.6
License-File: LICENSE
Requires-Dist: numpy
Requires-Dist: scipy
Requires-Dist: faiss-cpu
Requires-Dist: networkx
Requires-Dist: datasketch
Requires-Dist: statsmodels
